ingot_sqlite/__init__.py
ingot_sqlite/bootstrap/__init__.py
ingot_sqlite/bootstrap/base.py
ingot_sqlite/bootstrap/scaffolding/__init__.py
ingot_sqlite/contrib/__init__.py
ingot_sqlite/scripts/__init__.py
ingot_sqlite/scripts/ingot_sqlite.py
ingot_sqlite/tests/__init__.py
ingot_sqlite/tests/functionals/__init__.py
ingot_sqlite/tests/units/__init__.py
ingot_sqlite/tests/units/bootstrap/__init__.py
ingot_sqlite/tests/units/bootstrap/test_base.py
ingot_sqlite/tests/units/contrib/__init__.py
ingot_sqlite/tests/units/scripts/__init__.py
ingot_sqlite/tests/units/scripts/test_ingot_sqlite.py
ingot_sqlite-0.1.0.dist-info/LICENSE
ingot_sqlite-0.1.0.dist-info/METADATA
ingot_sqlite-0.1.0.dist-info/WHEEL
ingot_sqlite-0.1.0.dist-info/entry_points.txt
ingot_sqlite-0.1.0.dist-info/top_level.txt
ingot_sqlite-0.1.0.dist-info/RECORD
